simple_rom_manager-0.0.5.dist-info/DESCRIPTION.rst
simple_rom_manager-0.0.5.dist-info/METADATA
simple_rom_manager-0.0.5.dist-info/RECORD
simple_rom_manager-0.0.5.dist-info/WHEEL
simple_rom_manager-0.0.5.dist-info/entry_points.txt
simple_rom_manager-0.0.5.dist-info/metadata.json
simple_rom_manager-0.0.5.dist-info/pbr.json
simple_rom_manager-0.0.5.dist-info/top_level.txt
srm/__init__.py
srm/__main__.py
srm/cli.py
srm/config.py
srm/dat.py
srm/file.py
