Metadata-Version: 2.0
Name: simple-rom-manager
Version: 0.0.5
Summary: A basic command-line ROM set manager.
Home-page: https://github.com/cmcginty/simple-rom-manager
Author: Patrick C. McGinty
Author-email: casey.mcginty@gmail.com
License: MIT
Keywords: rom roms nointro datomatic retro gaming console snes nes games mame retropie fba
Platform: UNKNOWN
Classifier: Development Status :: 3 - Alpha
Classifier: Intended Audience :: End Users/Desktop
Classifier: License :: OSI Approved :: MIT License
Classifier: Natural Language :: English
Classifier: Operating System :: MacOS :: MacOS X
Classifier: Operating System :: POSIX :: Linux
Classifier: Programming Language :: Python :: 3.6
Classifier: Programming Language :: Python :: Implementation :: CPython
Classifier: Topic :: Games/Entertainment
Classifier: Topic :: System :: Archiving :: Compression
Classifier: Topic :: System :: Archiving
Classifier: Topic :: Utilities
Requires-Python: >=3.6
Requires-Dist: boltons (==17.2.0)
Requires-Dist: click (==6.7)
Requires-Dist: pbr (==3.1.1)
Requires-Dist: toml (==0.9.4)
